<mediawiki xmlns="http://www.mediawiki.org/xml/export-0.11/" xmlns:xsi="http://www.w3.org/2001/XMLSchema-instance" xsi:schemaLocation="http://www.mediawiki.org/xml/export-0.11/ http://www.mediawiki.org/xml/export-0.11.xsd" version="0.11" xml:lang="en">
  <siteinfo>
    <sitename>Shinto Wiki</sitename>
    <dbname>shintowiki</dbname>
    <base>https://shinto.miraheze.org/wiki/Main_Page</base>
    <generator>MediaWiki 1.45.3</generator>
    <case>first-letter</case>
    <namespaces>
      <namespace key="-2" case="first-letter">Media</namespace>
      <namespace key="-1" case="first-letter">Special</namespace>
      <namespace key="0" case="first-letter" />
      <namespace key="1" case="first-letter">Talk</namespace>
      <namespace key="2" case="first-letter">User</namespace>
      <namespace key="3" case="first-letter">User talk</namespace>
      <namespace key="4" case="first-letter">Project</namespace>
      <namespace key="5" case="first-letter">Project talk</namespace>
      <namespace key="6" case="first-letter">File</namespace>
      <namespace key="7" case="first-letter">File talk</namespace>
      <namespace key="8" case="first-letter">MediaWiki</namespace>
      <namespace key="9" case="first-letter">MediaWiki talk</namespace>
      <namespace key="10" case="first-letter">Template</namespace>
      <namespace key="11" case="first-letter">Template talk</namespace>
      <namespace key="12" case="first-letter">Help</namespace>
      <namespace key="13" case="first-letter">Help talk</namespace>
      <namespace key="14" case="first-letter">Category</namespace>
      <namespace key="15" case="first-letter">Category talk</namespace>
      <namespace key="420" case="first-letter">GeoJson</namespace>
      <namespace key="421" case="first-letter">GeoJson talk</namespace>
      <namespace key="828" case="first-letter">Module</namespace>
      <namespace key="829" case="first-letter">Module talk</namespace>
      <namespace key="860" case="first-letter">Item</namespace>
      <namespace key="861" case="first-letter">Item talk</namespace>
      <namespace key="862" case="first-letter">Property</namespace>
      <namespace key="863" case="first-letter">Property talk</namespace>
    </namespaces>
  </siteinfo>
  <page>
    <title>Help:Using the Wayback Machine</title>
    <ns>12</ns>
    <id>13388</id>
    <revision>
      <id>1151731</id>
      <timestamp>2025-04-10T14:56:58Z</timestamp>
      <contributor>
        <username>Immanuelle</username>
        <id>3</id>
      </contributor>
      <comment>Bot: Creating normal ill redirect for [[Category:Lua-based templates]].</comment>
      <origin>1151731</origin>
      <model>wikitext</model>
      <format>text/x-wiki</format>
      <text bytes="152" sha1="span1bfvve0dzkg44j9mfb46xr70z3w" xml:space="preserve">#redirect[[:en:Help:Using the Wayback Machine]]
[[Category:automatic wikipedia redirects]]
[[Category:pages created from Interlanguage links]]
[[ja:qq]]</text>
      <sha1>span1bfvve0dzkg44j9mfb46xr70z3w</sha1>
    </revision>
    <revision>
      <id>1151732</id>
      <parentid>1151731</parentid>
      <timestamp>2025-05-19T20:26:32Z</timestamp>
      <contributor>
        <username>Immanuelle</username>
        <id>3</id>
      </contributor>
      <comment>Bot: remove deleted category Pages created from Interlanguage links</comment>
      <origin>1151732</origin>
      <model>wikitext</model>
      <format>text/x-wiki</format>
      <text bytes="101" sha1="n9cib8cyhij7hs4c5h6x3imv0mdno4x" xml:space="preserve">#redirect[[:en:Help:Using the Wayback Machine]]
[[Category:automatic wikipedia redirects]]

[[ja:qq]]</text>
      <sha1>n9cib8cyhij7hs4c5h6x3imv0mdno4x</sha1>
    </revision>
    <revision>
      <id>1151733</id>
      <parentid>1151732</parentid>
      <timestamp>2025-05-22T07:40:57Z</timestamp>
      <contributor>
        <username>Immanuelle</username>
        <id>3</id>
      </contributor>
      <minor/>
      <comment>Bot: remove obsolete category Automatic wikipedia redirects</comment>
      <origin>1151733</origin>
      <model>wikitext</model>
      <format>text/x-wiki</format>
      <text bytes="59" sha1="5sc6jlzlix5mr1am90umcfcrj3r3i6n" xml:space="preserve">#redirect[[:en:Help:Using the Wayback Machine]]


[[ja:qq]]</text>
      <sha1>5sc6jlzlix5mr1am90umcfcrj3r3i6n</sha1>
    </revision>
    <revision>
      <id>13389</id>
      <timestamp>2025-11-22T14:00:15Z</timestamp>
      <contributor>
        <username>Immanuelle</username>
        <id>3</id>
      </contributor>
      <minor/>
      <comment>imported only latest revision from https://archive.org/details/miraheze-wiki-shintowiki-20251218 to avoid excessive disk usage, comment on the revision was Text replacement - "↵↵↵" to "
"</comment>
      <origin>13389</origin>
      <model>wikitext</model>
      <format>text/x-wiki</format>
      <text bytes="57" sha1="ajdercop2zzuzpm3mro473n1zvojqsn" xml:space="preserve">#redirect[[:en:Help:Using the Wayback Machine]]
[[ja:qq]]</text>
      <sha1>ajdercop2zzuzpm3mro473n1zvojqsn</sha1>
    </revision>
    <revision>
      <id>3697529</id>
      <parentid>13389</parentid>
      <timestamp>2026-05-02T22:31:08Z</timestamp>
      <contributor>
        <username>Immanuelle</username>
        <id>3</id>
      </contributor>
      <minor/>
      <comment>Text replacement - "#redirect[[:en:" to "redirect[[:en:"</comment>
      <origin>3697529</origin>
      <model>wikitext</model>
      <format>text/x-wiki</format>
      <text bytes="56" sha1="934cbt36hn19nb6lut50sezsrjd2lrv" xml:space="preserve">redirect[[:en:Help:Using the Wayback Machine]]
[[ja:qq]]</text>
      <sha1>934cbt36hn19nb6lut50sezsrjd2lrv</sha1>
    </revision>
    <revision>
      <id>3714192</id>
      <parentid>3697529</parentid>
      <timestamp>2026-05-06T15:53:05Z</timestamp>
      <contributor>
        <username>EmmaBot</username>
        <id>703</id>
      </contributor>
      <comment>Bot: consolidate 1 interlanguage link(s) into wikidata link template [[github:EmmaLeonhart/shintowiki-scripts/actions/runs/25441284107|time triggered pipeline]]</comment>
      <origin>3714192</origin>
      <model>wikitext</model>
      <format>text/x-wiki</format>
      <text bytes="71" sha1="0hy62ao4o2aialishvk7b7xe05x2s9p" xml:space="preserve">redirect[[:en:Help:Using the Wayback Machine]]
{{wikidata link||ja|qq}}</text>
      <sha1>0hy62ao4o2aialishvk7b7xe05x2s9p</sha1>
    </revision>
  </page>
</mediawiki>
